bdcdata/__init__.py
bdcdata/bdc.py
bdcdata/helpers.py
bdcdata-0.0.10.dist-info/METADATA
bdcdata-0.0.10.dist-info/WHEEL
bdcdata-0.0.10.dist-info/licenses/LICENSE.txt
bdcdata-0.0.10.dist-info/RECORD
